mosspy/__init__.py
mosspy/download_report.py
mosspy/moss.py
mosspy-1.0.9.dist-info/LICENSE
mosspy-1.0.9.dist-info/METADATA
mosspy-1.0.9.dist-info/WHEEL
mosspy-1.0.9.dist-info/top_level.txt
mosspy-1.0.9.dist-info/RECORD
