Metadata-Version: 2.1
Name: mosspy
Version: 1.0.9
Summary: A Python client for Moss: A System for Detecting Software Similarity
Home-page: https://github.com/soachishti/moss.py
Author: soachishti
Author-email: soachishti@outlook.com
License: UNKNOWN
Download-URL: https://github.com/soachishti/moss.py/releases
Keywords: moss,similarity,detecting,plagiarism
Platform: UNKNOWN
Requires-Dist: beautifulsoup4
Requires-Dist: lxml
